setup.py
guess_what_is_this_number/__init__.py
guess_what_is_this_number/guess_what_is_this_number.py
guess_what_is_this_number.egg-info/PKG-INFO
guess_what_is_this_number.egg-info/SOURCES.txt
guess_what_is_this_number.egg-info/dependency_links.txt
guess_what_is_this_number.egg-info/not-zip-safe
guess_what_is_this_number.egg-info/top_level.txt