Metadata-Version: 1.0
Name: guess-what-is-this-number
Version: 0.0.0.2
Summary: Game that askes user to guess a number between 0 and 100.
Home-page: UNKNOWN
Author: UNKNOWN
Author-email: UNKNOWN
License: UNKNOWN
Platform: UNKNOWN
